{
    "0": [
        "hills",
        "report",
        "morning",
        "1230",
        "welcome",
        "click",
        "view",
        "past",
        "editions",
        "hills\u00a01230\u00a0report",
        "presented",
        "happy",
        "newsletter",
        "gets",
        "speed",
        "important",
        "developments",
        "better",
        "alliance",
        "plus",
        "trends",
        "watch",
        "association",
        "races",
        "alexis"
    ],
    "1": [
        "trump",
        "donald",
        "president",
        "administration",
        "rally",
        "meeting",
        "wall",
        "washington",
        "host",
        "romney",
        "florida",
        "jr",
        "dont",
        "federal",
        "despite",
        "returns",
        "effort",
        "ukraine",
        "presidency",
        "judge",
        "made",
        "trial",
        "says",
        "office",
        "post"
    ],
    "2": [
        "klobuchar",
        "amy",
        "sen",
        "dminn",
        "minnesota",
        "woman",
        "experience",
        "debate",
        "democrat",
        "ad",
        "quarter",
        "iowa",
        "2020",
        "presidential",
        "would",
        "stage",
        "sunday",
        "bill",
        "candidate",
        "buy",
        "ethanol",
        "proposal",
        "saying",
        "hasnt",
        "punches"
    ],
    "3": [
        "years",
        "political",
        "american",
        "power",
        "politics",
        "protesters",
        "us",
        "year",
        "change",
        "kong",
        "climate",
        "war",
        "elections",
        "election",
        "party",
        "protests",
        "people",
        "china",
        "hong",
        "day",
        "government",
        "like",
        "one",
        "still",
        "today"
    ],
    "4": [
        "new",
        "york",
        "times",
        "police",
        "deadspin",
        "mayor",
        "editorials",
        "city",
        "hampshire",
        "bloomberg",
        "de",
        "around",
        "cnn",
        "book",
        "post",
        "ny",
        "special",
        "sports",
        "fox",
        "make",
        "blasio",
        "officer",
        "voting",
        "kavanaugh",
        "england"
    ],
    "5": [
        "news",
        "breaking",
        "broadcast",
        "video",
        "coverage",
        "exclusive",
        "interviews",
        "online",
        "abc",
        "find",
        "world",
        "get",
        "top",
        "national",
        "looms",
        "israeli",
        "challenge",
        "faces",
        "return",
        "story",
        "fall",
        "prices",
        "llenas",
        "channel",
        "uncertainty"
    ],
    "6": [
        "impeachment",
        "inquiry",
        "house",
        "democrats",
        "trump",
        "hearings",
        "nancy",
        "pelosi",
        "public",
        "hearing",
        "probe",
        "ambassador",
        "donald",
        "testimony",
        "testify",
        "president",
        "speaker",
        "ukraine",
        "key",
        "process",
        "committee",
        "read",
        "resolution",
        "republicans",
        "witnesses"
    ],
    "7": [
        "democratic",
        "presidential",
        "candidates",
        "debate",
        "warren",
        "2020",
        "elizabeth",
        "candidate",
        "care",
        "biden",
        "joe",
        "primary",
        "campaign",
        "race",
        "sanders",
        "health",
        "buttigieg",
        "field",
        "orourke",
        "warrens",
        "hillary",
        "attack",
        "iowa",
        "beto",
        "tom"
    ],
    "8": [
        "brexit",
        "boris",
        "johnson",
        "uk",
        "british",
        "minister",
        "prime",
        "european",
        "union",
        "deal",
        "parliament",
        "johnsons",
        "britain",
        "britains",
        "london",
        "eu",
        "russian",
        "uks",
        "leave",
        "talks",
        "election",
        "31",
        "delay",
        "northern",
        "plans"
    ],
    "9": [
        "president",
        "trumps",
        "donald",
        "ukraine",
        "trump",
        "vice",
        "ukrainian",
        "call",
        "former",
        "biden",
        "joe",
        "pence",
        "ukraines",
        "volodymyr",
        "zelensky",
        "giuliani",
        "us",
        "phone",
        "rudy",
        "son",
        "bidens",
        "carter",
        "investigate",
        "mike",
        "concerns"
    ]
}